<?xml version="1.0" encoding="UTF-8"?>
<actions>
        <action>
            <actionName>CUSTOM-Deploy-Sonatype</actionName>
            <displayName>Deploy to Sonatype</displayName>
            <goals>
                <goal>clean</goal>
                <goal>deploy</goal>
            </goals>
            <activatedProfiles>
                <activatedProfile>sonatype</activatedProfile>
                <activatedProfile>release-sign-artifacts</activatedProfile>
            </activatedProfiles>
        </action>
        <action>
            <actionName>CUSTOM-Deploy-Github</actionName>
            <displayName>Deploy to Github</displayName>
            <goals>
                <goal>clean</goal>
                <goal>deploy</goal>
            </goals>
            <activatedProfiles>
                <activatedProfile>github</activatedProfile>
                <activatedProfile>release-sign-artifacts</activatedProfile>
            </activatedProfiles>
        </action>
</actions>
